tests/__init__.py
tests/test_topic_queue_poller.py
tqp/__init__.py
tqp/datadog.py
tqp/exceptions.py
tqp/flask.py
tqp/newrelic.py
tqp/raven.py
tqp/threading_utils.py
tqp/topic.py
tqp/topic_queue_poller.py
tqp-1.0.0.dist-info/LICENSE
tqp-1.0.0.dist-info/METADATA
tqp-1.0.0.dist-info/WHEEL
tqp-1.0.0.dist-info/top_level.txt
tqp-1.0.0.dist-info/RECORD
