Metadata-Version: 2.1
Name: tqp
Version: 1.0.0
Summary: An opinionated library for pub/sub over SQS and SNS
Home-page: https://github.com/4Catalyzer/tqp
Author: Giacomo Tagliabue
Author-email: giacomo@gmail.com
License: MIT
Keywords: pub sub pubsub flask
Classifier: Development Status :: 3 - Alpha
Classifier: License :: OSI Approved :: MIT License
Classifier: Operating System :: OS Independent
Classifier: Programming Language :: Python
Classifier: Programming Language :: Python :: 3
Classifier: Programming Language :: Python :: 3.6
Classifier: Programming Language :: Python :: 3.7
Classifier: Programming Language :: Python :: 3.8
Classifier: Programming Language :: Python :: 3 :: Only
Requires-Python: >=3.6
License-File: LICENSE
Requires-Dist: boto3
Provides-Extra: dev
Requires-Dist: pytest ; extra == 'dev'
Requires-Dist: fourmat ~=0.4.3 ; extra == 'dev'
Requires-Dist: pre-commit ; extra == 'dev'
Requires-Dist: moto[server] ; extra == 'dev'
Requires-Dist: boto3 ; extra == 'dev'
